{
	"backtrace" : 0,
	"backtraceGraph" : 
	{
		"commands" : [],
		"files" : 
		[
			"out/build/_deps/googletest-src/googletest/CMakeLists.txt"
		],
		"nodes" : 
		[
			{
				"file" : 0
			}
		]
	},
	"id" : "gtest_autogen_timestamp_deps::@1ea2dfc0605fe3ab2a3f",
	"isGeneratorProvided" : true,
	"name" : "gtest_autogen_timestamp_deps",
	"paths" : 
	{
		"build" : "_deps/googletest-build/googletest",
		"source" : "out/build/_deps/googletest-src/googletest"
	},
	"sourceGroups" : 
	[
		{
			"name" : "",
			"sourceIndexes" : 
			[
				0
			]
		},
		{
			"name" : "CMake Rules",
			"sourceIndexes" : 
			[
				1
			]
		}
	],
	"sources" : 
	[
		{
			"backtrace" : 0,
			"isGenerated" : true,
			"path" : "out/build/_deps/googletest-build/googletest/CMakeFiles/gtest_autogen_timestamp_deps",
			"sourceGroupIndex" : 0
		},
		{
			"backtrace" : 0,
			"isGenerated" : true,
			"path" : "out/build/_deps/googletest-build/googletest/CMakeFiles/gtest_autogen_timestamp_deps.rule",
			"sourceGroupIndex" : 1
		}
	],
	"type" : "UTILITY"
}
